agentset/__init__.py
agentset/_version.py
agentset/basesdk.py
agentset/documents.py
agentset/hosting_sdk.py
agentset/httpclient.py
agentset/ingestjobs.py
agentset/namespace_sdk.py
agentset/namespaces.py
agentset/py.typed
agentset/sdk.py
agentset/sdkconfiguration.py
agentset/search.py
agentset/uploads.py
agentset/_hooks/__init__.py
agentset/_hooks/registration.py
agentset/_hooks/sdkhooks.py
agentset/_hooks/types.py
agentset/errors/__init__.py
agentset/errors/agentsetdefaulterror.py
agentset/errors/agentseterror.py
agentset/errors/badrequest_error.py
agentset/errors/conflict_error.py
agentset/errors/forbidden_error.py
agentset/errors/internalservererror.py
agentset/errors/inviteexpired_error.py
agentset/errors/no_response_error.py
agentset/errors/notfound_error.py
agentset/errors/ratelimitexceeded_error.py
agentset/errors/responsevalidationerror.py
agentset/errors/unauthorized_error.py
agentset/errors/unprocessableentity_error.py
agentset/models/__init__.py
agentset/models/azure_embedding_config.py
agentset/models/azure_embedding_configoutput.py
agentset/models/badrequest_error.py
agentset/models/batch_payload.py
agentset/models/batch_payload_input.py
agentset/models/conflict_error.py
agentset/models/crawl_payload.py
agentset/models/crawl_payloadoutput.py
agentset/models/create_vector_store_config.py
agentset/models/createbatchuploadop.py
agentset/models/createingestjobop.py
agentset/models/createnamespaceop.py
agentset/models/createuploadop.py
agentset/models/deletedocumentop.py
agentset/models/deletehostingop.py
agentset/models/deleteingestjobop.py
agentset/models/deletenamespaceop.py
agentset/models/document.py
agentset/models/document_config.py
agentset/models/document_configoutput.py
agentset/models/document_status.py
agentset/models/embedding_model_config.py
agentset/models/embedding_model_configoutput.py
agentset/models/enablehostingop.py
agentset/models/file_payload.py
agentset/models/file_payloadoutput.py
agentset/models/forbidden_error.py
agentset-0.6.4.dist-info/licenses/LICENSE.md
agentset-0.6.4.dist-info/METADATA
agentset-0.6.4.dist-info/WHEEL
agentset-0.6.4.dist-info/top_level.txt
agentset-0.6.4.dist-info/RECORD
