Metadata-Version: 2.4
Name: agentset
Version: 0.6.4
Summary: Python Client SDK Generated by Speakeasy.
Author: Speakeasy
Project-URL: repository, https://github.com/agentset-ai/agentset-python.git
Requires-Python: >=3.9.2
License-File: LICENSE.md
Requires-Dist: httpcore>=1.0.9
Requires-Dist: httpx>=0.28.1
Requires-Dist: jsonpath-python>=1.0.6
Requires-Dist: pydantic>=2.11.2
Dynamic: license-file
